gloc/__init__.py
gloc/geocoordinates.py
gloc-0.2.1.dist-info/LICENSE
gloc-0.2.1.dist-info/WHEEL
gloc-0.2.1.dist-info/METADATA
gloc-0.2.1.dist-info/RECORD
