Metadata-Version: 2.1
Name: gloc
Version: 0.2.1
Summary: Automates creation of requests to, and parsing of response from Google's geocoding API.
Author-email: Anders Petersson <a.m.petersson@protonmail.com>
Requires-Python: >=3.11
Classifier: License :: OSI Approved :: Apache Software License
Requires-Dist: requests >= 2.22.0
Project-URL: Source, https://gitlab.com/AMPOV/gloc
